[{"id":1,"email":"fereverv@naver.com","firstname":"Kim","lastname":"sungsoo","password":"$2a$08$AQkeOOS.D.uqCtQYbAECu.VIHTtN0wMqPBxclldBFYpZLMVTI7DWi","birthday":"2005-05-03T15:00:00.000Z","profileImage":"/static/image/user/default_user_profile_image.jpg"},{"id":2,"email":"fereverv@naver.comF","firstname":"Kim","lastname":"sungsoo","password":"$2a$08$Zsm3lP4Grkh/PX5CkYtrkeUPoV9iUgwBSMJm5D4zntQmLwRCJy3Xa","birthday":"2005-05-03T15:00:00.000Z","profileImage":"/static/image/user/default_user_profile_image.jpg"}]